AsteriskRealtimeData/Settings.py
AsteriskRealtimeData/__init__.py
AsteriskRealtimeData/__main__.py
AsteriskRealtimeData/api.py
AsteriskRealtimeData/environments.py
AsteriskRealtimeData/application/__init__.py
AsteriskRealtimeData/application/agent_repository.py
AsteriskRealtimeData/application/agent_service.py
AsteriskRealtimeData/application/call_repository.py
AsteriskRealtimeData/application/call_service.py
AsteriskRealtimeData/application/last_status_repository.py
AsteriskRealtimeData/application/last_status_service.py
AsteriskRealtimeData/application/mascara_ipaddress_repository.py
AsteriskRealtimeData/application/mascara_ipaddress_service.py
AsteriskRealtimeData/application/pause_reason_repository.py
AsteriskRealtimeData/application/pause_reasons_service.py
AsteriskRealtimeData/application/peer_repository.py
AsteriskRealtimeData/application/peer_service.py
AsteriskRealtimeData/application/queue_member_repository.py
AsteriskRealtimeData/application/queue_member_repository_v1.py
AsteriskRealtimeData/application/queue_member_service.py
AsteriskRealtimeData/application/queue_member_service_v1.py
AsteriskRealtimeData/application/queue_status_repository.py
AsteriskRealtimeData/application/queue_status_service.py
AsteriskRealtimeData/domain/__init__.py
AsteriskRealtimeData/domain/entity.py
AsteriskRealtimeData/domain/search_by_criteria_vo.py
AsteriskRealtimeData/domain/update_vo.py
AsteriskRealtimeData/domain/agent/__init__.py
AsteriskRealtimeData/domain/agent/agent.py
AsteriskRealtimeData/domain/agent/agent_search_criteria_vo.py
AsteriskRealtimeData/domain/agent/agent_update_vo.py
AsteriskRealtimeData/domain/agent/agent_vo.py
AsteriskRealtimeData/domain/call/__init__.py
AsteriskRealtimeData/domain/call/call.py
AsteriskRealtimeData/domain/call/call_search_criteria_vo.py
AsteriskRealtimeData/domain/call/call_update_vo.py
AsteriskRealtimeData/domain/call/call_vo.py
AsteriskRealtimeData/domain/last_status/__init__.py
asteriskrealtimedata-1.1.15.dist-info/METADATA
asteriskrealtimedata-1.1.15.dist-info/WHEEL
asteriskrealtimedata-1.1.15.dist-info/top_level.txt
asteriskrealtimedata-1.1.15.dist-info/RECORD
