Metadata-Version: 2.1
Name: asteriskrealtimedata
Version: 1.1.15
Summary: API for manage realtime data about asterisk status
Home-page: UNKNOWN
Author: Juares Vermelho Diaz (CL3k)
Author-email: jvermelho@cl3k.com
License: UNKNOWN
Keywords: Asterisk realtime
Platform: UNKNOWN
Requires-Dist: antidote (==1.0.0)
Requires-Dist: fastrlock (==0.5)
Requires-Dist: pymongo (==3.12.0)
